LICENSE
MANIFEST.in
README.md
setup.py
django_payex.egg-info/PKG-INFO
django_payex.egg-info/SOURCES.txt
django_payex.egg-info/dependency_links.txt
django_payex.egg-info/top_level.txt
djpayex/__init__.py
djpayex/admin.py
djpayex/managers.py
djpayex/models.py
djpayex/urls.py
djpayex/utils.py
djpayex/views.py