Metadata-Version: 1.0
Name: django-payex
Version: 0.2.1
Summary: Django application for saving statuses and receiving callbacks from the PayEx API.
Home-page: https://github.com/funkbit/django-payex
Author: Funkbit
Author-email: post@funkbit.no
License: BSD
Platform: UNKNOWN
Classifier: Development Status :: 3 - Alpha
Classifier: Framework :: Django
Classifier: Intended Audience :: Developers
Classifier: License :: OSI Approved :: BSD License
Classifier: Programming Language :: Python
Classifier: Programming Language :: Python :: 2.6
Classifier: Programming Language :: Python :: 2.7
